alpaca_historical_extract/__init__.py
alpaca_historical_extract/api_library.py
alpaca_historical_extract/core_library.py
alpaca_historical_extract/dbmsIO.py
alpaca_historical_extract/extract_library.py
alpaca_historical_extract/hub.py
alpaca_historical_extract/load_library.py
alpaca_historical_extract/main.py
alpaca_historical_extract/multiprocessing_library.py
alpaca_historical_extract/transform_library.py
alpaca_historical_extract-1.25.0.dist-info/LICENSE.txt
alpaca_historical_extract-1.25.0.dist-info/METADATA
alpaca_historical_extract-1.25.0.dist-info/WHEEL
alpaca_historical_extract-1.25.0.dist-info/top_level.txt
alpaca_historical_extract-1.25.0.dist-info/RECORD
