Metadata-Version: 2.1
Name: alpaca-historical-extract
Version: 1.25.0
Summary: README.md
Home-page: https://github.com/Cole-Dylewski/Alpaca-Stock-Algo
Author: Cole Dylewski
Author-email: cole.dylewski@gmail.com
License: MIT
Keywords: Alpaca Stock Extraction
Platform: UNKNOWN
License-File: LICENSE.txt
Requires-Dist: pytz
Requires-Dist: tzdata
Requires-Dist: pandas-market-calendars
Requires-Dist: pandas
Requires-Dist: requests
Requires-Dist: numpy
Requires-Dist: alpaca-trade-api
Requires-Dist: yahoo-fin
Requires-Dist: yfinance
